ossiq/__init__.py
ossiq/__main__.py
ossiq/cli.py
ossiq/messages.py
ossiq/settings.py
ossiq/timeutil.py
ossiq/adapters/__init__.py
ossiq/adapters/api.py
ossiq/adapters/api_github.py
ossiq/adapters/api_interfaces.py
ossiq/adapters/api_npm.py
ossiq/adapters/api_osv.py
ossiq/adapters/api_pypi.py
ossiq/adapters/detectors.py
ossiq/adapters/package_managers/__init__.py
ossiq/adapters/package_managers/api.py
ossiq/adapters/package_managers/api_npm.py
ossiq/adapters/package_managers/api_pip.py
ossiq/adapters/package_managers/api_pip_classic.py
ossiq/adapters/package_managers/api_uv.py
ossiq/adapters/package_managers/utils.py
ossiq/commands/__init__.py
ossiq/commands/export.py
ossiq/commands/scan.py
ossiq/domain/__init__.py
ossiq/domain/common.py
ossiq/domain/cve.py
ossiq/domain/exceptions.py
ossiq/domain/package.py
ossiq/domain/packages_manager.py
ossiq/domain/project.py
ossiq/domain/repository.py
ossiq/domain/version.py
ossiq/service/__init__.py
ossiq/service/project.py
ossiq/service/common/__init__.py
ossiq/service/common/package_versions.py
ossiq/ui/__init__.py
ossiq/ui/interfaces.py
ossiq/ui/registry.py
ossiq/ui/system.py
ossiq/ui/html/__init__.py
ossiq/ui/html/filter_format_highlight_days.py
ossiq/ui/html/tag_versions_difference.py
ossiq/ui/html/template_environment.py
ossiq/ui/html_templates/filter_format_highlight_days.html
ossiq/ui/html_templates/tag_versions_difference.html
ossiq/ui/renderers/__init__.py
ossiq/ui/renderers/export/__init__.py
ossiq/ui/renderers/export/csv.py
ossiq/ui/renderers/export/csv_datapackage.py
ossiq/ui/renderers/export/csv_schema_registry.py
ossiq/ui/renderers/export/json.py
ossiq/ui/renderers/export/json_schema_registry.py
ossiq/ui/renderers/export/models.py
ossiq/ui/renderers/export/schemas/export_schema_v1.0.json
ossiq/ui/renderers/export/schemas/csv/cves-schema-v1.0.json
ossiq/ui/renderers/export/schemas/csv/packages-schema-v1.0.json
ossiq/ui/renderers/export/schemas/csv/summary-schema-v1.0.json
ossiq/ui/renderers/scan/__init__.py
ossiq-0.1.5.dist-info/METADATA
ossiq-0.1.5.dist-info/WHEEL
ossiq-0.1.5.dist-info/entry_points.txt
ossiq-0.1.5.dist-info/licenses/AUTHORS
ossiq-0.1.5.dist-info/licenses/LICENSE
ossiq-0.1.5.dist-info/RECORD
