Metadata-Version: 2.4
Name: ossiq
Version: 0.1.5
Summary: Utility to forecast risks associated with currently installed packages updates
Project-URL: bugs, https://github.com/ossiq/ossiq/issues
Project-URL: changelog, https://github.com/ossiq/ossiq/blob/master/changelog.md
Project-URL: homepage, https://github.com/ossiq/ossiq
Project-URL: repository, https://github.com/ossiq/ossiq.git
Author-email: Maksym Klymyshyn <klymyshyn@gmail.com>
Maintainer-email: Maksym Klymyshyn <klymyshyn@gmail.com>
License-Expression: AGPL-3.0-only
License-File: AUTHORS
License-File: LICENSE
Keywords: engineering,maintenance,tech debt,techdebt,toc
Classifier: Development Status :: 3 - Alpha
Classifier: Intended Audience :: Developers
Classifier: Intended Audience :: Information Technology
Classifier: Operating System :: OS Independent
Classifier: Programming Language :: Python :: 3
Classifier: Programming Language :: Python :: 3 :: Only
Classifier: Programming Language :: Python :: 3.11
Classifier: Programming Language :: Python :: 3.12
Classifier: Programming Language :: Python :: 3.13
Classifier: Programming Language :: Python :: 3.14
Classifier: Topic :: Scientific/Engineering :: Information Analysis
Classifier: Topic :: Security
Classifier: Topic :: Software Development
Classifier: Topic :: Software Development :: Build Tools
Classifier: Topic :: Software Development :: Quality Assurance
Classifier: Topic :: Software Development :: Version Control
Classifier: Topic :: System :: Monitoring
Classifier: Topic :: System :: Software Distribution
Classifier: Topic :: Utilities
Requires-Python: >=3.11
Requires-Dist: common-expression-language>=0.5.3
Requires-Dist: frictionless~=5.18.1
Requires-Dist: hatch>=1.15.1
Requires-Dist: jinja2~=3.1.6
Requires-Dist: jsonschema~=4.26.0
Requires-Dist: packaging>=25.0
Requires-Dist: pandas>=2.3.3
Requires-Dist: petl~=1.7.15
Requires-Dist: pydantic~=2.12.4
Requires-Dist: requests~=2.32.5
Requires-Dist: rich~=14.2.0
Requires-Dist: semver~=3.0.4
Requires-Dist: termcolor~=3.2.0
Requires-Dist: typer~=0.20.0
Provides-Extra: dev
Requires-Dist: coverage~=7.13.1; extra == 'dev'
Requires-Dist: ipdb~=0.13.13; extra == 'dev'
Requires-Dist: pylint~=4.0.4; extra == 'dev'
Requires-Dist: pytest~=9.0.2; extra == 'dev'
Requires-Dist: ruff~=0.14.10; extra == 'dev'
Requires-Dist: ty~=0.0.8; extra == 'dev'
Provides-Extra: docs
Requires-Dist: mkdocs-material~=9.7.1; extra == 'docs'
Requires-Dist: mkdocs-nav-weight~=0.3.0; extra == 'docs'
Requires-Dist: mkdocstrings~=1.0.0; extra == 'docs'
Requires-Dist: mkdocs~=1.6.1; extra == 'docs'
